napari_pyclesperanto_assistant/__init__.py
napari_pyclesperanto_assistant/_advanced_statistics.py
napari_pyclesperanto_assistant/_convert_to_numpy.py
napari_pyclesperanto_assistant/_napari_cle_functions.py
napari_pyclesperanto_assistant/_napari_plugin.py
napari_pyclesperanto_assistant/_neighborhood_statistics.py
napari_pyclesperanto_assistant/_statistics_of_labeled_pixels.py
napari_pyclesperanto_assistant/_gui/_Assistant.py
napari_pyclesperanto_assistant/_gui/__init__.py
napari_pyclesperanto_assistant/_gui/_select_gpu.py
napari_pyclesperanto_assistant/_gui/icons/any_image.png
napari_pyclesperanto_assistant/_gui/icons/binarize.png
napari_pyclesperanto_assistant/_gui/icons/binary_image.png
napari_pyclesperanto_assistant/_gui/icons/combine.png
napari_pyclesperanto_assistant/_gui/icons/compare_label_images.png
napari_pyclesperanto_assistant/_gui/icons/filter.png
napari_pyclesperanto_assistant/_gui/icons/generate_code....png
napari_pyclesperanto_assistant/_gui/icons/intensity_image.png
napari_pyclesperanto_assistant/_gui/icons/intensity_image_filtered.png
napari_pyclesperanto_assistant/_gui/icons/intensity_image_with_background.png
napari_pyclesperanto_assistant/_gui/icons/intensity_image_with_noise.png
napari_pyclesperanto_assistant/_gui/icons/label.png
napari_pyclesperanto_assistant/_gui/icons/label_filters.png
napari_pyclesperanto_assistant/_gui/icons/label_image.png
napari_pyclesperanto_assistant/_gui/icons/label_image_processed.png
napari_pyclesperanto_assistant/_gui/icons/label_neighbor_filters.png
napari_pyclesperanto_assistant/_gui/icons/map.png
napari_pyclesperanto_assistant/_gui/icons/measure.png
napari_pyclesperanto_assistant/_gui/icons/measure_labeled_image.png
napari_pyclesperanto_assistant/_gui/icons/measure_labels.png
napari_pyclesperanto_assistant/_gui/icons/mesh.png
napari_pyclesperanto_assistant/_gui/icons/mesh_image.png
napari_pyclesperanto_assistant/_gui/icons/parametric_image.png
napari_pyclesperanto_assistant/_gui/icons/process_labels.png
napari_pyclesperanto_assistant-0.25.0.dist-info/LICENSE
napari_pyclesperanto_assistant-0.25.0.dist-info/METADATA
napari_pyclesperanto_assistant-0.25.0.dist-info/WHEEL
napari_pyclesperanto_assistant-0.25.0.dist-info/entry_points.txt
napari_pyclesperanto_assistant-0.25.0.dist-info/top_level.txt
napari_pyclesperanto_assistant-0.25.0.dist-info/RECORD
