Metadata-Version: 2.1
Name: napari_pyclesperanto_assistant
Version: 0.25.0
Summary: GPU-accelerated image processing in napari using OpenCL
Home-page: https://github.com/clesperanto/napari_pyclesperanto_assistant
Author: Robert Haase, Talley Lambert
Author-email: robert.haase@tu-dresden.de
License: BSD-3-Clause
Project-URL: Bug Tracker, https://github.com/clEsperanto/napari_pyclesperanto_assistant/issues
Project-URL: Documentation, https://github.com/clEsperanto/napari_pyclesperanto_assistant/
Project-URL: Source Code, https://github.com/clEsperanto/napari_pyclesperanto_assistant
Project-URL: User Support, https://forum.image.sc/tag/clij
Classifier: Programming Language :: Python :: 3
Classifier: License :: OSI Approved :: BSD License
Classifier: Operating System :: OS Independent
Classifier: Framework :: napari
Classifier: Intended Audience :: Science/Research
Classifier: Development Status :: 3 - Alpha
Requires-Python: >=3.9
License-File: LICENSE
Requires-Dist: napari-plugin-engine>=0.1.4
Requires-Dist: pyopencl
Requires-Dist: toolz
Requires-Dist: scikit-image
Requires-Dist: napari>=0.4.15
Requires-Dist: pyclesperanto-prototype>=0.24.5
Requires-Dist: pyclesperanto==0.14.2
Requires-Dist: magicgui
Requires-Dist: numpy!=1.19.4
Requires-Dist: pyperclip
Requires-Dist: loguru
Requires-Dist: jupytext
Requires-Dist: jupyter
Requires-Dist: pandas
Requires-Dist: napari-tools-menu>=0.1.8
Requires-Dist: napari-time-slicer>=0.4.0
Requires-Dist: napari-skimage-regionprops>=0.2.0
Requires-Dist: napari-workflows>=0.1.1
Requires-Dist: napari-assistant>=0.2.0
